jpzipcode/__init__.py
jpzipcode/extracter.py
jpzipcode/resolver.py
jpzipcode/fastapi/__init__.py
jpzipcode/fastapi/endpoint.py
jpzipcode-0.3.0.dist-info/METADATA
jpzipcode-0.3.0.dist-info/WHEEL
jpzipcode-0.3.0.dist-info/licenses/LICENSE
jpzipcode-0.3.0.dist-info/RECORD
